naclo/__init__.py
naclo/dataframes.py
naclo/fragments.py
naclo/mol_conversion.py
naclo/mol_stats.py
naclo/neutralize.py
naclo/visualization.py
test/__init__.py
test/test_dataframes.py
test/test_fragments.py
test/test_mol_conversion.py
test/test_mol_stats.py
test/test_neutralize.py
test/test_visualization.py
naclo-0.1.8.dist-info/METADATA
naclo-0.1.8.dist-info/WHEEL
naclo-0.1.8.dist-info/top_level.txt
naclo-0.1.8.dist-info/RECORD
