Metadata-Version: 2.1
Name: naclo
Version: 0.1.8
Summary: Cleaning toolset for small molecule drug discovery datasets
Home-page: https://github.com/jwgerlach00/naclo
Author: Jacob Gerlach
Author-email: jwgerlach00@gmail.com
License: MIT
Platform: UNKNOWN
Requires-Python: >=3.6, <3.8
Requires-Dist: pandas
Requires-Dist: rdkit-pypi
